[
  {
    "ContainingType": "EndPoint.Controllers.BasketController",
    "Method": "Add",
    "RelativePath": "api/Basket/Add",
    "HttpMethod": "POST",
    "IsController": true,
    "Order": 0,
    "Parameters": [
      {
        "Name": "productId",
        "Type": "System.String",
        "IsRequired": false
      },
      {
        "Name": "userId",
        "Type": "System.String",
        "IsRequired": false
      }
    ],
    "ReturnTypes": []
  },
  {
    "ContainingType": "EndPoint.Controllers.BasketController",
    "Method": "GetAll",
    "RelativePath": "api/Basket/GetAll",
    "HttpMethod": "GET",
    "IsController": true,
    "Order": 0,
    "Parameters": [
      {
        "Name": "userId",
        "Type": "System.String",
        "IsRequired": false
      }
    ],
    "ReturnTypes": []
  },
  {
    "ContainingType": "EndPoint.Controllers.CommentController",
    "Method": "Add",
    "RelativePath": "api/Comment/Add",
    "HttpMethod": "POST",
    "IsController": true,
    "Order": 0,
    "Parameters": [
      {
        "Name": "text",
        "Type": "System.String",
        "IsRequired": false
      },
      {
        "Name": "userId",
        "Type": "System.String",
        "IsRequired": false
      },
      {
        "Name": "productId",
        "Type": "System.String",
        "IsRequired": false
      }
    ],
    "ReturnTypes": []
  },
  {
    "ContainingType": "EndPoint.Controllers.CommentController",
    "Method": "GetAll",
    "RelativePath": "api/Comment/GetAll",
    "HttpMethod": "GET",
    "IsController": true,
    "Order": 0,
    "Parameters": [
      {
        "Name": "userId",
        "Type": "System.String",
        "IsRequired": false
      }
    ],
    "ReturnTypes": []
  },
  {
    "ContainingType": "EndPoint.Controllers.CommentController",
    "Method": "Update",
    "RelativePath": "api/Comment/Update",
    "HttpMethod": "POST",
    "IsController": true,
    "Order": 0,
    "Parameters": [
      {
        "Name": "CommentId",
        "Type": "System.String",
        "IsRequired": false
      },
      {
        "Name": "Text",
        "Type": "System.String",
        "IsRequired": false
      },
      {
        "Name": "isDelete",
        "Type": "System.String",
        "IsRequired": false
      }
    ],
    "ReturnTypes": []
  },
  {
    "ContainingType": "EndPoint.Controllers.ProductController",
    "Method": "Add",
    "RelativePath": "api/Product/Add",
    "HttpMethod": "POST",
    "IsController": true,
    "Order": 0,
    "Parameters": [
      {
        "Name": "addDto",
        "Type": "Application.Command.DTO.ProductDTO.AddDTO",
        "IsRequired": true
      }
    ],
    "ReturnTypes": []
  },
  {
    "ContainingType": "EndPoint.Controllers.ProductController",
    "Method": "GetAll",
    "RelativePath": "api/Product/GetAll",
    "HttpMethod": "GET",
    "IsController": true,
    "Order": 0,
    "Parameters": [],
    "ReturnTypes": []
  },
  {
    "ContainingType": "EndPoint.Controllers.ProductController",
    "Method": "Remove",
    "RelativePath": "api/Product/Remove",
    "HttpMethod": "POST",
    "IsController": true,
    "Order": 0,
    "Parameters": [
      {
        "Name": "deleteDto",
        "Type": "Application.Command.DTO.ProductDTO.DeleteDTO",
        "IsRequired": true
      }
    ],
    "ReturnTypes": []
  },
  {
    "ContainingType": "EndPoint.Controllers.ProductController",
    "Method": "Update",
    "RelativePath": "api/Product/Update",
    "HttpMethod": "POST",
    "IsController": true,
    "Order": 0,
    "Parameters": [
      {
        "Name": "updateDto",
        "Type": "Application.Command.DTO.ProductDTO.ProductUpdateDTO",
        "IsRequired": true
      }
    ],
    "ReturnTypes": []
  },
  {
    "ContainingType": "EndPoint.Controllers.UserController",
    "Method": "GetAll",
    "RelativePath": "api/User/GetAll",
    "HttpMethod": "GET",
    "IsController": true,
    "Order": 0,
    "Parameters": [],
    "ReturnTypes": []
  },
  {
    "ContainingType": "EndPoint.Controllers.UserController",
    "Method": "Register",
    "RelativePath": "api/User/Register",
    "HttpMethod": "POST",
    "IsController": true,
    "Order": 0,
    "Parameters": [
      {
        "Name": "signUpDto",
        "Type": "Application.Command.DTO.User.SignUpDTO",
        "IsRequired": true
      }
    ],
    "ReturnTypes": []
  },
  {
    "ContainingType": "EndPoint.Controllers.UserController",
    "Method": "RemoveAccount",
    "RelativePath": "api/User/RemoveAccount",
    "HttpMethod": "DELETE",
    "IsController": true,
    "Order": 0,
    "Parameters": [
      {
        "Name": "removeAccountDto",
        "Type": "Application.Command.DTO.User.RemoveAccountDTO",
        "IsRequired": true
      }
    ],
    "ReturnTypes": []
  },
  {
    "ContainingType": "EndPoint.Controllers.UserController",
    "Method": "Update",
    "RelativePath": "api/User/Update",
    "HttpMethod": "POST",
    "IsController": true,
    "Order": 0,
    "Parameters": [
      {
        "Name": "updateDto",
        "Type": "Application.Command.DTO.User.UpdateDTO",
        "IsRequired": true
      }
    ],
    "ReturnTypes": []
  }
]